PikaBus/PikaBus.py
PikaBus/PikaBusSetup.py
PikaBus/PikaErrorHandler.py
PikaBus/PikaProperties.py
PikaBus/PikaSerializer.py
PikaBus/__init__.py
PikaBus/abstractions/AbstractPikaBus.py
PikaBus/abstractions/AbstractPikaBusSetup.py
PikaBus/abstractions/AbstractPikaErrorHandler.py
PikaBus/abstractions/AbstractPikaMessageHandler.py
PikaBus/abstractions/AbstractPikaProperties.py
PikaBus/abstractions/AbstractPikaSerializer.py
PikaBus/abstractions/__init__.py
PikaBus/tools/PikaConstants.py
PikaBus/tools/PikaOutgoing.py
PikaBus/tools/PikaSteps.py
PikaBus/tools/PikaTools.py
PikaBus/tools/__init__.py
PikaBus-1.3.7.dist-info/LICENSE
PikaBus-1.3.7.dist-info/METADATA
PikaBus-1.3.7.dist-info/WHEEL
PikaBus-1.3.7.dist-info/top_level.txt
PikaBus-1.3.7.dist-info/RECORD
