Metadata-Version: 2.1
Name: PikaBus
Version: 1.3.7
Summary: Pika bus wrapper for amqp messaging with RabbitMq
Home-page: UNKNOWN
Author: Hans Erik Heggem
Author-email: hans.erik.heggem@gmail.com
License: UNKNOWN
Project-URL: Documentation, https://pikabus.readthedocs.org/
Project-URL: Source, https://github.com/hansehe/PikaBus
Keywords: pika RabbitMQ amqp
Platform: all
Classifier: Development Status :: 5 - Production/Stable
Classifier: Intended Audience :: Developers
Classifier: Topic :: Communications
Classifier: Topic :: Internet
Classifier: Topic :: Software Development :: Libraries
Classifier: Topic :: Software Development :: Libraries :: Python Modules
Classifier: Topic :: System :: Networking
Classifier: License :: OSI Approved :: MIT License
Classifier: Operating System :: MacOS
Classifier: Operating System :: POSIX
Classifier: Operating System :: Microsoft
Classifier: Programming Language :: Python :: 3
Classifier: Programming Language :: Python :: 3.6
Classifier: Programming Language :: Python :: 3.7
Classifier: Programming Language :: Python :: 3.8
License-File: LICENSE
Requires-Dist: pika
Provides-Extra: dev
Requires-Dist: check-manifest ; extra == 'dev'
Provides-Extra: test
Requires-Dist: coverage ; extra == 'test'
